source_microsoft_sharepoint/__init__.py
source_microsoft_sharepoint/exceptions.py
source_microsoft_sharepoint/run.py
source_microsoft_sharepoint/source.py
source_microsoft_sharepoint/spec.py
source_microsoft_sharepoint/stream_reader.py
source_microsoft_sharepoint/utils.py
airbyte_source_microsoft_sharepoint-0.10.4.dist-info/METADATA
airbyte_source_microsoft_sharepoint-0.10.4.dist-info/WHEEL
airbyte_source_microsoft_sharepoint-0.10.4.dist-info/entry_points.txt
airbyte_source_microsoft_sharepoint-0.10.4.dist-info/RECORD
