Metadata-Version: 2.1
Name: airbyte-source-microsoft-sharepoint
Version: 0.10.4
Summary: Source implementation for Microsoft SharePoint.
Home-page: https://airbyte.com
License: ELv2
Author: Airbyte
Author-email: contact@airbyte.io
Requires-Python: >=3.11,<3.12
Classifier: License :: Other/Proprietary License
Classifier: Programming Language :: Python :: 3
Classifier: Programming Language :: Python :: 3.11
Requires-Dist: Office365-REST-Python-Client (==2.5.5)
Requires-Dist: airbyte-cdk[file-based] (>=6,<7)
Requires-Dist: msal (==1.27.0)
Requires-Dist: smart-open (==6.4.0)
Project-URL: Documentation, https://docs.airbyte.com/integrations/sources/microsoft-sharepoint
Project-URL: Repository, https://github.com/airbytehq/airbyte
